{
    "0": {
        "title": "Hakataism",
        "href": "/portfolios/hakataism/index.html",
        "about": "",
        "builtWith": ["jQuery", "Bootstrap", "Photoshop"],
        "time": "2014"
    },
    "1": {
        "title": "Fallout Hack Tool",
        "href": "/portfolios/falloutHackTool/index.html",
        "about": "",
        "builtWith": ["jQuery"],
        "time": "2017"
    },
    "2": {
        "title": "CHIKA Music Awards 2017",
        "href": "/portfolios/chikaMusicAwards2017/index.html",
        "about": "",
        "builtWith": ["jQuery", "Bootstrap"],
        "time": "2017"
    },    
    "3": {
        "title": "Node Chat App",
        "href": "https://github.com/AsukaCHikaru/node-chat-app",
        "about": "",
        "builtWith": ["Node.js", "jQuery"],
        "time": "2017"
    },
    "4": {
        "title": "CHIKA Music Awards 2018",
        "href": "http://chikamusicawards.asukachikaru.com",
        "about": "Exclusive site for my personal annual music awards, as rewind of my favorite music of the year.",
        "builtWith": ["React"],
        "time": "2018",
        "img": "chika-music-awards.png"
    },
    "5": {
        "title": "The work is undone.",
        "href": "https://blog.asukachikaru.com",
        "about": "My blog. Completely handmade, 0 blog host service used.",
        "builtWith": ["React Redux", "React Router"],
        "time": "2019",
        "img": "the-work-is-undone.png"
    },
    "6": {
        "title": "asukachikaru.com v3",
        "href": "https://asukachikaru.com",
        "about": "This site. Third iteration of my resume site.",
        "builtWith": ["React"],
        "time": "2019",
        "img": "asukachikaru-com.png"
    }
}